README.rst
setup.py
memo/__init__.py
memo/memo.py
python_memo.egg-info/PKG-INFO
python_memo.egg-info/SOURCES.txt
python_memo.egg-info/dependency_links.txt
python_memo.egg-info/top_level.txt