Metadata-Version: 1.0
Name: python-memo
Version: 0.1.0
Summary: Decorators to memoize function results (also for classes)
Home-page: http://github.com/enricobacis/python-memo
Author: Enrico Bacis
Author-email: enrico.bacis@gmail.com
License: MIT
Keywords: memo memoize dynamic programming cache decorator instance
Platform: UNKNOWN
